LICENSE
MANIFEST.in
README.md
requirements.txt
setup.py
bin/clairvoyance_v1.py
clairvoyance/__init__.py
clairvoyance/bayesian.py
clairvoyance/feature_selection.py
clairvoyance/legacy.py
clairvoyance/transformations.py
clairvoyance/utils.py
clairvoyance_feature_selection.egg-info/PKG-INFO
clairvoyance_feature_selection.egg-info/SOURCES.txt
clairvoyance_feature_selection.egg-info/dependency_links.txt
clairvoyance_feature_selection.egg-info/requires.txt
clairvoyance_feature_selection.egg-info/top_level.txt