Metadata-Version: 2.4
Name: clairvoyance_feature_selection
Version: 2025.8.13
Summary: AutoML simultaneous bayesian hyperparameter optimization and feature selection
Home-page: https://github.com/jolespin/clairvoyance
Author: Josh L. Espinoza
Author-email: jol.espinoz@gmail.com
License: Apache 2.0
License-File: LICENSE
Requires-Dist: pyexeggutor>=2025.2.19
Requires-Dist: memory-profiler
Requires-Dist: feature_engine>=1.6.2
Requires-Dist: optuna>=3.6.1
Requires-Dist: scikit-learn>=1.0
Requires-Dist: scipy>=1.0
Requires-Dist: numpy>=1.13
Requires-Dist: pandas>=1.2.4
Requires-Dist: tqdm>=4.19
Dynamic: author
Dynamic: author-email
Dynamic: home-page
Dynamic: license
Dynamic: license-file
Dynamic: requires-dist
Dynamic: summary
